jenks_natural_breaks/__init__.py
jenks_natural_breaks/_jenks_matrices.c
jenks_natural_breaks/_jenks_matrices.pyd
jenks_natural_breaks/_jenks_matrices_build.py
jenks_natural_breaks-0.2.0.dist-info/DESCRIPTION.rst
jenks_natural_breaks-0.2.0.dist-info/METADATA
jenks_natural_breaks-0.2.0.dist-info/RECORD
jenks_natural_breaks-0.2.0.dist-info/WHEEL
jenks_natural_breaks-0.2.0.dist-info/metadata.json
jenks_natural_breaks-0.2.0.dist-info/top_level.txt
