Metadata-Version: 2.0
Name: jenks-natural-breaks
Version: 0.2.0
Summary: CFFI accelerated Jenks classification
Home-page: https://github.com/cwalv/jenks_natural_breaks
Author: Charlie Arnold
Author-email: c@cwa.lv
License: MIT license
Keywords: jenks,gis,statistics
Platform: UNKNOWN
Classifier: Development Status :: 5 - Production/Stable
Classifier: Intended Audience :: Developers
Classifier: License :: OSI Approved :: MIT License
Classifier: Operating System :: Unix
Classifier: Operating System :: POSIX
Classifier: Operating System :: Microsoft :: Windows
Classifier: Programming Language :: Python
Classifier: Programming Language :: Python :: 2.7
Classifier: Programming Language :: Python :: 3
Classifier: Programming Language :: Python :: 3.4
Classifier: Programming Language :: Python :: 3.5
Classifier: Programming Language :: Python :: 3.6
Classifier: Programming Language :: Python :: Implementation :: CPython
Classifier: Programming Language :: Python :: Implementation :: PyPy
Classifier: Topic :: Utilities
Requires-Python: >=2.7, !=3.0.*, !=3.1.*, !=3.2.*, !=3.3.*
Requires-Dist: cffi (>=1.0.0)
Requires-Dist: numpy (>=1.13.0)
Provides-Extra: test
Requires-Dist: pytest; extra == 'test'
